pygradflow/__init__.py
pygradflow/active_set.py
pygradflow/callbacks.py
pygradflow/cons_problem.py
pygradflow/controller.py
pygradflow/deriv_check.py
pygradflow/display.py
pygradflow/eval.py
pygradflow/implicit_func.py
pygradflow/integration/__init__.py
pygradflow/integration/events.py
pygradflow/integration/flow.py
pygradflow/integration/integration_solver.py
pygradflow/integration/problem_switches.py
pygradflow/integration/restricted_flow.py
pygradflow/iterate.py
pygradflow/linear_solver/__init__.py
pygradflow/linear_solver/cholesky_solver.py
pygradflow/linear_solver/gmres_solver.py
pygradflow/linear_solver/linear_solver.py
pygradflow/linear_solver/lu_solver.py
pygradflow/linear_solver/ma57_solver.py
pygradflow/linear_solver/minres_solver.py
pygradflow/linear_solver/mumps_solver.py
pygradflow/linear_solver/ssids_solver.py
pygradflow/log.py
pygradflow/newton.py
pygradflow/params.py
pygradflow/penalty.py
pygradflow/problem.py
pygradflow/py.typed
pygradflow/result.py
pygradflow/runners/cutest_runner.py
pygradflow/runners/instance.py
pygradflow/runners/mps_runner.py
pygradflow/runners/qplib_runner.py
pygradflow/runners/runner.py
pygradflow/scale.py
pygradflow/solver.py
pygradflow/status.py
pygradflow/step/box_control.py
pygradflow/step/box_solver.py
pygradflow/step/cond_estimate.py
pygradflow/step/distance_ratio_control.py
pygradflow/step/exact_control.py
pygradflow/step/fixed_control.py
pygradflow/step/linear_solver.py
pygradflow/step/newton_control.py
pygradflow/step/opti_control.py
pygradflow/step/residuum_ratio_control.py
pygradflow/step/solver/__init__.py
pygradflow/step/solver/asymmetric_step_solver.py
pygradflow/step/solver/extended_step_solver.py
pygradflow/step/solver/scaled_step_solver.py
pygradflow/step/solver/standard_step_solver.py
pygradflow/step/solver/step_solver.py
pygradflow/step/solver/symmetric_step_solver.py
pygradflow/step/step_control.py
pygradflow/step/step_solver_error.py
pygradflow/timer.py
pygradflow/transform.py
pygradflow/util.py
pygradflow-0.5.24.dist-info/LICENSE
pygradflow-0.5.24.dist-info/METADATA
pygradflow-0.5.24.dist-info/WHEEL
pygradflow-0.5.24.dist-info/RECORD
