Metadata-Version: 2.3
Name: pygradflow
Version: 0.5.24
Summary: PyGradFlow is a simple implementation of the sequential homotopy method to be used to solve general nonlinear programs.
Author: Christoph Hansknecht
Author-email: christoph.hansknecht@tu-clausthal.de
Requires-Python: >=3.10,<4.0
Classifier: Programming Language :: Python :: 3
Classifier: Programming Language :: Python :: 3.10
Classifier: Programming Language :: Python :: 3.11
Classifier: Programming Language :: Python :: 3.12
Classifier: Programming Language :: Python :: 3.13
Requires-Dist: cyipopt (>=1.4.1)
Requires-Dist: matplotlib (>=3.7.0)
Requires-Dist: numpy (>=2.0)
Requires-Dist: pyyaml (>=6.0.0)
Requires-Dist: scipy (>=1.14)
Requires-Dist: termcolor (>=2.3.0)
Project-URL: Documentation, https://pygradflow.readthedocs.io
Project-URL: Repository, https://github.com/chrhansk/pygradflow
